Metadata-Version: 1.0
Name: pro-music-player
Version: 1.0
Summary: Este pacote fornecerá ferramentas de áudio
Home-page: UNKNOWN
Author: João Victor Júlio
Author-email: julio.guerra.dev@gmail.com
License: UNKNOWN
Keywords: audio,ondas sonoras,processamento,graves
Platform: UNKNOWN
